startup.py
BucketUtils.egg-info/PKG-INFO
BucketUtils.egg-info/SOURCES.txt
BucketUtils.egg-info/dependency_links.txt
BucketUtils.egg-info/requires.txt
BucketUtils.egg-info/top_level.txt
DecisionTreeBktUtil/__init__.py
DecisionTreeBktUtil/getColBktFromDF.py